Metadata-Version: 1.0
Name: pacsquery
Version: 1.0.6
Summary: Query a PACS through an intermediary service, "pfdcm" (not included).
Home-page: https://github.com/FNNDSC/pfmisc
Author: Rudolph Pienaar
Author-email: rudolph.pienaar@gmail.com
License: MIT
Platform: UNKNOWN
